bpcm/__init__.py
bpcm/template.py
bpcm-0.1.dist-info/METADATA
bpcm-0.1.dist-info/WHEEL
bpcm-0.1.dist-info/top_level.txt
bpcm-0.1.dist-info/RECORD
