Metadata-Version: 2.1
Name: bpcm
Version: 0.1
Summary: Python bpcmPackage
Home-page: UNKNOWN
Author: UNKNOWN
Author-email: UNKNOWN
License: UNKNOWN
Platform: UNKNOWN
Requires-Dist: pandas
